dreamy/__init__.py
dreamy/annotate.py
dreamy/data/__init__.py
dreamy/data/custom_datasets.py
dreamy/data/get_data.py
dreamy/util/__init__.py
dreamy/util/_anonimise.py
dreamy/util/_embeddings_util.py
dreamy/util/_models_identifier.py
dreamy/util/_reduction_util.py
dreamy/util/_test_custom_architecture.py
dreamy/util/architecture.py
dreamy/util/classification_pipeline.py
dreamy/util/generation_pipeline.py
dreamy/util/hvdc_decodings.py
dreamy/util/train_util.py
dreamy/util/util.py
dreamy-0.1.5.1.dist-info/METADATA
dreamy-0.1.5.1.dist-info/WHEEL
dreamy-0.1.5.1.dist-info/top_level.txt
dreamy-0.1.5.1.dist-info/RECORD
